package_name/__init__.py
package_name/calculadora.py
package_name/file1_name.py
package_name/file2_name.py
calculadora_imc_novo_dio-0.1.0.dist-info/METADATA
calculadora_imc_novo_dio-0.1.0.dist-info/WHEEL
calculadora_imc_novo_dio-0.1.0.dist-info/top_level.txt
calculadora_imc_novo_dio-0.1.0.dist-info/RECORD
