Metadata-Version: 2.2
Name: calculadora_imc_novo_dio
Version: 0.1.0
Summary: Uma calculadora simples de IMC
Home-page: https://github.com/ThiagoEpiphanio/calculadora-imc
Author: Thiago Epiphanio
Author-email: seuemail@example.com
Classifier: Programming Language :: Python :: 3
Classifier: License :: OSI Approved :: MIT License
Classifier: Operating System :: OS Independent
Requires-Python: >=3.6
Dynamic: author
Dynamic: author-email
Dynamic: classifier
Dynamic: description
Dynamic: description-content-type
Dynamic: home-page
Dynamic: requires-python
Dynamic: summary
